jax_hf/__init__.py
jax_hf/jax_modules.py
jax_hf/main.py
jax_hf/mixing.py
jax_hf/utils.py
jax_hf/wrappers.py
jax_hf-1.0.2.dist-info/licenses/LICENSE
jax_hf-1.0.2.dist-info/licenses/THIRD_PARTY_NOTICES.md
jax_hf-1.0.2.dist-info/METADATA
jax_hf-1.0.2.dist-info/WHEEL
jax_hf-1.0.2.dist-info/top_level.txt
jax_hf-1.0.2.dist-info/RECORD
