Metadata-Version: 2.4
Name: jax_hf
Version: 1.0.2
Summary: A package that provides a jax-based Hartree-Fock optimization solver for simple continuum models.
Author: Tobias Wolf
Author-email: public@wolft.xyz
License: BSD 2-Clause License
Project-URL: Homepage, https://github.com/skilledwolf/jax_hf
Project-URL: Source, https://github.com/skilledwolf/jax_hf
Project-URL: Issues, https://github.com/skilledwolf/jax_hf/issues
Keywords: physics,condensed matter,hartree fock,mean field,scf
Classifier: Development Status :: 3 - Alpha
Classifier: Intended Audience :: Science/Research
Classifier: License :: OSI Approved :: BSD License
Classifier: Programming Language :: Python :: 3
Requires-Python: >=3.11
License-File: LICENSE
License-File: THIRD_PARTY_NOTICES.md
Requires-Dist: jax
Requires-Dist: optimistix
Requires-Dist: optax
Dynamic: license-file
